django_knockout_modeler-0.11.0.dist-info/DESCRIPTION.rst
django_knockout_modeler-0.11.0.dist-info/METADATA
django_knockout_modeler-0.11.0.dist-info/metadata.json
django_knockout_modeler-0.11.0.dist-info/pbr.json
django_knockout_modeler-0.11.0.dist-info/RECORD
django_knockout_modeler-0.11.0.dist-info/top_level.txt
django_knockout_modeler-0.11.0.dist-info/WHEEL
knockout_modeler/__init__.py
knockout_modeler/ko.py
knockout_modeler/tests.py
knockout_modeler/templates/knockout_modeler/model.js
knockout_modeler/templatetags/__init__.py
knockout_modeler/templatetags/knockout.py
