Metadata-Version: 2.0
Name: django-knockout-modeler
Version: 0.11.0
Summary: Super easy ModelViews for knockout.js for your Django models
Home-page: https://github.com/Miserlou/django-knockout-modeler
Author: Rich Jones
Author-email: rich@openwatch.net
License: MIT License
Platform: UNKNOWN
Classifier: Environment :: Web Environment
Classifier: Framework :: Django
Classifier: Intended Audience :: Developers
Classifier: License :: OSI Approved :: Apache Software License
Classifier: Operating System :: OS Independent
Classifier: Programming Language :: Python
Classifier: Programming Language :: Python :: 2.7
Classifier: Topic :: Internet :: WWW/HTTP
Classifier: Topic :: Internet :: WWW/HTTP :: Dynamic Content
Requires-Dist: coverage (>=4.0.2)
Requires-Dist: Django (>=1.11)
Requires-Dist: django-fake-model (>=0.1.1)
Requires-Dist: Js2Py (>=0.30)
Requires-Dist: nose (>=1.3.7)
Requires-Dist: simplejson (>=3.8.1)
Requires-Dist: wheel (>=0.24.0)
